cepton_sdk/__init__.py
cepton_sdk/api.py
cepton_sdk/c.py
cepton_sdk/capture_replay.py
cepton_sdk/core.py
cepton_sdk/export.py
cepton_sdk/load.py
cepton_sdk/plot.py
cepton_sdk/point.py
cepton_sdk/sensor.py
cepton_sdk/settings.py
cepton_sdk/common/__init__.py
cepton_sdk/common/c.py
cepton_sdk/common/general.py
cepton_sdk/common/transform.py
cepton_sdk-1.17.8.data/scripts/cepton_capture.py
cepton_sdk-1.17.8.data/scripts/cepton_capture_gui.py
cepton_sdk-1.17.8.data/scripts/cepton_clip.py
cepton_sdk-1.17.8.data/scripts/cepton_export.py
cepton_sdk-1.17.8.data/scripts/cepton_export_serial.py
cepton_sdk-1.17.8.data/scripts/cepton_georeference.py
cepton_sdk-1.17.8.data/scripts/cepton_list_sensors.py
cepton_util/VERSION
cepton_util/__init__.py
cepton_util/capture.py
cepton_util/common.py
cepton_util/gui.py
cepton_sdk-1.17.8.dist-info/METADATA
cepton_sdk-1.17.8.dist-info/WHEEL
cepton_sdk-1.17.8.dist-info/top_level.txt
cepton_sdk-1.17.8.dist-info/RECORD
